dp/__init__.py
dp/phonemizer.py
dp/preprocess.py
dp/result.py
dp/train.py
dp/configs/__init__.py
dp/configs/autoreg_config.yaml
dp/configs/forward_config.yaml
dp/model/__init__.py
dp/model/model.py
dp/model/predictor.py
dp/model/utils.py
dp/preprocessing/__init__.py
dp/preprocessing/text.py
dp/preprocessing/utils.py
dp/training/__init__.py
dp/training/dataset.py
dp/training/decorators.py
dp/training/evaluation.py
dp/training/losses.py
dp/training/metrics.py
dp/training/trainer.py
dp/utils/__init__.py
dp/utils/io.py
dp/utils/logging.py
g2p_phonemizer-0.1.1.dist-info/licenses/LICENSE
g2p_phonemizer-0.1.1.dist-info/METADATA
g2p_phonemizer-0.1.1.dist-info/WHEEL
g2p_phonemizer-0.1.1.dist-info/top_level.txt
g2p_phonemizer-0.1.1.dist-info/RECORD
