Metadata-Version: 2.4
Name: g2p-phonemizer
Version: 0.1.1
Summary: Grapheme to phoneme conversion with deep learning.
Author: Feiteng Li
Author-email: lifeiteng0422@gmail.com
License: MIT
Classifier: Development Status :: 4 - Beta
Classifier: Intended Audience :: Developers
Classifier: Intended Audience :: Education
Classifier: Intended Audience :: Science/Research
Classifier: License :: OSI Approved :: MIT License
Classifier: Operating System :: POSIX :: Linux
Classifier: Operating System :: MacOS :: MacOS X
Classifier: Operating System :: Microsoft :: Windows
Classifier: Programming Language :: Python :: 3
Classifier: Programming Language :: Python :: 3.9
Classifier: Programming Language :: Python :: 3.10
Classifier: Programming Language :: Python :: 3.11
Classifier: Programming Language :: Python :: 3.12
Classifier: Programming Language :: Python :: 3.13
Classifier: Topic :: Scientific/Engineering
Classifier: Topic :: Software Development :: Libraries
Classifier: Topic :: Software Development :: Libraries :: Python Modules
License-File: LICENSE
Requires-Dist: torch>=2.1.0
Requires-Dist: tqdm>=4.38.0
Requires-Dist: PyYAML>=5.1
Requires-Dist: tensorboard
Requires-Dist: certifi>=2022.12.7
Requires-Dist: wheel>=0.38.0
Requires-Dist: setuptools>=65.5.1
Requires-Dist: cached-path
Requires-Dist: num2words
Provides-Extra: tests
Requires-Dist: pytest-cov; extra == "tests"
Provides-Extra: docs
Requires-Dist: mkdocs; extra == "docs"
Requires-Dist: mkdocs-material; extra == "docs"
Provides-Extra: dev
Requires-Dist: bumpversion; extra == "dev"
Dynamic: author
Dynamic: author-email
Dynamic: classifier
Dynamic: description
Dynamic: description-content-type
Dynamic: license
Dynamic: license-file
Dynamic: provides-extra
Dynamic: requires-dist
Dynamic: summary
